{"nodes": [{"id": "home_vcretu_dotfiles_nvim_config_nvim_lua_plugins_lsp_lua", "label": "lsp.lua", "file_type": "code", "source_file": "nvim/.config/nvim/lua/plugins/lsp.lua", "source_location": "L1"}, {"id": "plugins_lsp_map", "label": "map()", "file_type": "code", "source_file": "nvim/.config/nvim/lua/plugins/lsp.lua", "source_location": "L54"}], "edges": [{"source": "home_vcretu_dotfiles_nvim_config_nvim_lua_plugins_lsp_lua", "target": "plugins_lsp_map", "relation": "contains", "confidence": "EXTRACTED", "source_file": "nvim/.config/nvim/lua/plugins/lsp.lua", "source_location": "L54", "weight": 1.0}], "raw_calls": [{"caller_nid": "plugins_lsp_map", "callee": "vim.keymap.set", "is_member_call": false, "source_file": "/home/vcretu/dotfiles/nvim/.config/nvim/lua/plugins/lsp.lua", "source_location": "L55"}]}